[
    [
        {
            "url": "./assets/images/cz/towns/litomerice-1.jpg",
            "source": {
                "name": "Wikimedia Commons",
                "url": "https://commons.wikimedia.org/wiki/File:Star%C3%A1_radnice_z_n%C3%A1m%C4%9Bst%C3%AD.JPG"
            }
        },
        {
            "url": "./assets/images/cz/towns/litomerice-2.jpg",
            "source": {
                "name": "Wikimedia Commons",
                "url": "https://commons.wikimedia.org/wiki/File:Litom%C4%9B%C5%99ice_Sv_%C5%A0t%C4%9Bp%C3%A1n.jpg"
            }
        },
        {
            "url": "./assets/images/cz/towns/litomerice-3.jpg",
            "source": {
                "name": "Wikimedia Commons",
                "url": "https://commons.wikimedia.org/wiki/File:Litom%C4%9B%C5%99ice_n%C3%A1m%C4%9Bst%C3%AD_U_%C4%8Cern%C3%A9ho_orla_a_kostel.jpg"
            }
        },
        {
            "url": "./assets/images/cz/towns/litomerice-4.jpg",
            "source": {
                "name": "Wikimedia Commons",
                "url": "https://commons.wikimedia.org/wiki/File:LITOM.jpg"
            }
        },
        {
            "url": "./assets/images/cz/towns/litomerice-5.jpg",
            "source": {
                "name": "Wikimedia Commons",
                "url": "https://commons.wikimedia.org/wiki/File:Litom%C4%9B%C5%99ice_(CZ)_-_Marktplatz_-_Panorama_(tone-mapping).jpg"
            }
        },
        {
            "url": "./assets/images/cz/towns/litomerice-6.jpg",
            "source": {
                "name": "Wikimedia Commons",
                "url": "https://commons.wikimedia.org/wiki/File:Litom%C4%9B%C5%99ice,_Katedr%C3%A1la_svat%C3%A9ho_%C5%A0t%C4%9Bp%C3%A1na_Dm356255-1754_vanaf_Ml%C3%A9kojedy_IMG_7792_2018-08-12_12.08.jpg"
            }
        },
        {
            "url": "./assets/images/cz/towns/litomerice-7.jpg",
            "source": {
                "name": "Wikimedia Commons",
                "url": "https://commons.wikimedia.org/wiki/File:Litom%C4%9B%C5%99ice_n%C3%A1m%C4%9Bst%C3%AD_1.jpg"
            }
        }
    ],
    {
        "url": "./assets/images/cz/towns/litomerice-map.png",
        "source": {
            "name": "Wikipedia",
            "url": "https://cs.wikipedia.org/wiki/Litom%C4%9B%C5%99ice"
        }
    }
]