[
    [
        {
            "url": "./assets/images/cz/capitals/prague/janackovo-nabrezi-1.jpg",
            "source": {
                "name": "Wikimedia Commons",
                "url": "https://commons.wikimedia.org/wiki/File:Lode_u_Detskeho_Ostrova.jpg"
            }
        }
    ],
    {
        "url": "./assets/images/cz/capitals/prague/janackovo-nabrezi-map.png",
        "source": {
            "name": "Wikimedia, OpenStreetMap",
            "url": "https://cs.wikipedia.org/wiki/Jan%C3%A1%C4%8Dkovo_n%C3%A1b%C5%99e%C5%BE%C3%AD#/map/0"
        }
    }
]